topsis/__init__.py
topsis/__main__.py
TOPSIS_Aman_101803676-0.0.1.dist-info/LICENSE
TOPSIS_Aman_101803676-0.0.1.dist-info/METADATA
TOPSIS_Aman_101803676-0.0.1.dist-info/WHEEL
TOPSIS_Aman_101803676-0.0.1.dist-info/entry_points.txt
TOPSIS_Aman_101803676-0.0.1.dist-info/top_level.txt
TOPSIS_Aman_101803676-0.0.1.dist-info/RECORD
