Metadata-Version: 2.1
Name: TOPSIS-Aman-101803676
Version: 0.0.1
Summary: It calculates the TOPSIS score and rank
Home-page: UNKNOWN
Author: Aman Sharma
License: MIT
Platform: UNKNOWN
Classifier: License :: OSI Approved :: MIT License
Classifier: Programming Language :: Python :: 3.6
Classifier: Programming Language :: Python :: 3.7
Classifier: Programming Language :: Python :: 3.8
